envreplace.py
envreplace-1.0.0.dist-info/entry_points.txt
envreplace-1.0.0.dist-info/LICENSE
envreplace-1.0.0.dist-info/WHEEL
envreplace-1.0.0.dist-info/METADATA
envreplace-1.0.0.dist-info/RECORD
